{
    "boxShadow": "none",
    "iconSVG": "/static/media/icon.f2c34197dbcf03595098986de898928f.svg",
    "topRow": 29,
    "tooltip": "Your .env file content.\nEach environment variable is a line.",
    "labelWidth": "5",
    "type": "INPUT_WIDGET_V2",
    "animateLoading": true,
    "resetOnSubmit": true,
    "leftColumn": 6,
    "dynamicBindingPathList": [
        {"key": "accentColor"},
        {"key": "borderRadius"}
    ],
    "labelStyle": "",
    "inputType": "MULTI_LINE_TEXT",
    "isDisabled": false,
    "isRequired": false,
    "dynamicHeight": "AUTO_HEIGHT",
    "accentColor": "{{appsmith.theme.colors.primaryColor}}",
    "showStepArrows": false,
    "isVisible": true,
    "version": 2,
    "tags": [
        "Suggested",
        "Inputs"
    ],
    "isLoading": false,
    "borderRadius": "{{appsmith.theme.borderRadius.appBorderRadius}}",
    "originalBottomRow": 39,
    "mobileBottomRow": 37,
    "widgetName": "input_be_env_vars",
    "displayName": "Input",
    "searchTags": [
        "form",
        "text input",
        "number",
        "textarea"
    ],
    "bottomRow": 39,
    "parentRowSpace": 10,
    "autoFocus": false,
    "hideCard": false,
    "mobileRightColumn": 25,
    "parentColumnSpace": 6.9375,
    "dynamicTriggerPathList": [],
    "labelPosition": "Top",
    "key": "3xm6hy9nwl",
    "labelTextSize": "0.875rem",
    "isDeprecated": false,
    "rightColumn": 56,
    "widgetId": "hqaw07xy8b",
    "minWidth": 450,
    "label": "Environment file",
    "parentId": "kc3297tric",
    "labelAlignment": "left",
    "renderMode": "CANVAS",
    "mobileTopRow": 30,
    "responsiveBehavior": "fill",
    "originalTopRow": 29,
    "mobileLeftColumn": 5,
    "maxDynamicHeight": 9000,
    "shouldAllowAutofill": false,
    "iconAlign": "left",
    "defaultText": "",
    "minDynamicHeight": 4
}